kuibit/__init__.py
kuibit/argparse_helper.py
kuibit/attr_dict.py
kuibit/cactus_ascii_utils.py
kuibit/cactus_grid_functions.py
kuibit/cactus_horizons.py
kuibit/cactus_multipoles.py
kuibit/cactus_pittnull.py
kuibit/cactus_scalars.py
kuibit/cactus_timers.py
kuibit/cactus_twopunctures.py
kuibit/cactus_waves.py
kuibit/data/CE1.dat
kuibit/data/CE2.dat
kuibit/data/ETB.dat
kuibit/data/ETD.dat
kuibit/data/KAGRA_VRSED.dat
kuibit/data/aLIGO_PLUS.dat
kuibit/data/aLIGO_ZDHP.dat
kuibit/data/voyager.dat
kuibit/frequencyseries.py
kuibit/grid_data.py
kuibit/grid_data_utils.py
kuibit/gw_mismatch.py
kuibit/gw_utils.py
kuibit/hor_utils.py
kuibit/masks.py
kuibit/numerical.py
kuibit/sensitivity_curves.py
kuibit/series.py
kuibit/simdir.py
kuibit/tensor.py
kuibit/timeseries.py
kuibit/tree.py
kuibit/uniform_grid.py
kuibit/unitconv.py
kuibit/visualize_matplotlib.py
kuibit-1.5.0.dist-info/LICENSE
kuibit-1.5.0.dist-info/METADATA
kuibit-1.5.0.dist-info/WHEEL
kuibit-1.5.0.dist-info/RECORD
