Metadata-Version: 2.1
Name: kuibit
Version: 1.5.0
Summary: Read and analyze Einstein Toolkit simulations.
Home-page: https://github.com/sbozzolo/kuibit
License: GPL-3.0-or-later
Author: Gabriele Bozzola
Author-email: gbozzola@caltech.edu
Maintainer: Gabriele Bozzola
Maintainer-email: gbozzola@caltech.edu
Requires-Python: >=3.7,<3.13
Classifier: License :: OSI Approved :: GNU General Public License v3 or later (GPLv3+)
Classifier: Programming Language :: Python :: 3
Classifier: Programming Language :: Python :: 3.7
Classifier: Programming Language :: Python :: 3.8
Classifier: Programming Language :: Python :: 3.9
Classifier: Programming Language :: Python :: 3.10
Classifier: Programming Language :: Python :: 3.11
Classifier: Programming Language :: Python :: 3.12
Provides-Extra: full
Requires-Dist: ConfigArgParse (>=1.2.3,<2.0.0)
Requires-Dist: argcomplete (>=2.0.0,<3.0.0)
Requires-Dist: h5py (>=3.2.0,<4.0.0)
Requires-Dist: matplotlib (>=3.5.0,<4.0.0)
Requires-Dist: motionpicture (>=0.2.0,<1)
Requires-Dist: numba (>=0.50,<1) ; (python_version < "3.8") and (extra == "full")
Requires-Dist: numba (>=0.57,<1) ; (python_version >= "3.8") and (extra == "full")
Requires-Dist: numpy (>=1.21.0,<2.0.0) ; python_version < "3.9"
Requires-Dist: numpy (>=1.26.0,<2.0.0) ; python_version >= "3.9"
Requires-Dist: openpmd-api (>=0.14.0,<0.15.0) ; python_version < "3.8"
Requires-Dist: openpmd-api (>=0.15.2,<0.16.0) ; python_full_version > "3.8.0"
Requires-Dist: py-expression-eval (>=0.3.14,<1)
Requires-Dist: scipy (>=1.11.0,<2.0.0) ; python_version >= "3.12"
Requires-Dist: scipy (>=1.7.0,<2.0.0) ; python_version < "3.8"
Requires-Dist: scipy (>=1.9.0,<2.0.0) ; python_full_version > "3.8.0" and python_version < "3.9"
Requires-Dist: tikzplotlib (>=0.9.13,<1)
Project-URL: Bug Tracker, https://github.com/sbozzolo/kuibit/issues
Project-URL: Documentation, https://sbozzolo.github.io/kuibit
Project-URL: Repository, https://github.com/sbozzolo/kuibit
